zentinel/__init__.py
zentinel/_argparse.py
zentinel/_constants.py
zentinel/_output.py
zentinel/_ports.py
zentinel/_results.py
zentinel/_scanner.py
zentinel/main.py
zentinel-0.0.3.dist-info/LICENSE
zentinel-0.0.3.dist-info/METADATA
zentinel-0.0.3.dist-info/WHEEL
zentinel-0.0.3.dist-info/entry_points.txt
zentinel-0.0.3.dist-info/top_level.txt
zentinel-0.0.3.dist-info/RECORD
